{
    "2003-02-03": [
        {
            "@k": 1,
            "APR": 1.2941176470588236,
            "APR_norm": 0.038062283737024215,
            "Avg_rank": 110.41176470588235,
            "Avg_num_recs": 1.0,
            "Coverage": 0.06984126984126984,
            "Gini": 0.28609625668449196,
            "Entropy": 2.907328555321631,
            "APLT": 0.7058823529411765
        },
        {
            "@k": 2,
            "APR": 1.1470588235294117,
            "APR_norm": 0.03373702422145328,
            "Avg_rank": 88.20588235294117,
            "Avg_num_recs": 2.0,
            "Coverage": 0.07301587301587302,
            "Gini": 0.5933503836317137,
            "Entropy": 2.1468114582207605,
            "APLT": 0.8529411764705882
        },
        {
            "@k": 5,
            "APR": 1.1470588235294117,
            "APR_norm": 0.03373702422145328,
            "Avg_rank": 88.20588235294117,
            "Avg_num_recs": 2.0,
            "Coverage": 0.07301587301587302,
            "Gini": 0.5933503836317137,
            "Entropy": 2.1468114582207605,
            "APLT": 0.8529411764705882
        },
        {
            "@k": 10,
            "APR": 1.1470588235294117,
            "APR_norm": 0.03373702422145328,
            "Avg_rank": 88.20588235294117,
            "Avg_num_recs": 2.0,
            "Coverage": 0.07301587301587302,
            "Gini": 0.5933503836317137,
            "Entropy": 2.1468114582207605,
            "APLT": 0.8529411764705882
        }
    ],
    "2003-02-04": [
        {
            "@k": 1,
            "APR": 1.3666666666666667,
            "APR_norm": 0.04555555555555557,
            "Avg_rank": 113.53333333333333,
            "Avg_num_recs": 1.0,
            "Coverage": 0.07641196013289037,
            "Gini": 0.17971014492753626,
            "Entropy": 3.0602870926086956,
            "APLT": 0.5666666666666667
        },
        {
            "@k": 2,
            "APR": 1.6833333333333333,
            "APR_norm": 0.05611111111111112,
            "Avg_rank": 66.76666666666667,
            "Avg_num_recs": 2.0,
            "Coverage": 0.07641196013289037,
            "Gini": 0.5681159420289855,
            "Entropy": 2.055740873322212,
            "APLT": 0.2833333333333333
        },
        {
            "@k": 5,
            "APR": 1.6833333333333333,
            "APR_norm": 0.05611111111111112,
            "Avg_rank": 66.76666666666667,
            "Avg_num_recs": 2.0,
            "Coverage": 0.07641196013289037,
            "Gini": 0.5681159420289855,
            "Entropy": 2.055740873322212,
            "APLT": 0.2833333333333333
        },
        {
            "@k": 10,
            "APR": 1.6833333333333333,
            "APR_norm": 0.05611111111111112,
            "Avg_rank": 66.76666666666667,
            "Avg_num_recs": 2.0,
            "Coverage": 0.07641196013289037,
            "Gini": 0.5681159420289855,
            "Entropy": 2.055740873322212,
            "APLT": 0.2833333333333333
        }
    ],
    "2003-02-05": [
        {
            "@k": 1,
            "APR": 1.0333333333333334,
            "APR_norm": 0.03444444444444445,
            "Avg_rank": 112.96666666666667,
            "Avg_num_recs": 1.0,
            "Coverage": 0.0539568345323741,
            "Gini": 0.3422222222222222,
            "Entropy": 2.4996543458216145,
            "APLT": 0.9
        },
        {
            "@k": 2,
            "APR": 1.5166666666666666,
            "APR_norm": 0.05055555555555557,
            "Avg_rank": 63.983333333333334,
            "Avg_num_recs": 2.0,
            "Coverage": 0.05755395683453238,
            "Gini": 0.5979166666666667,
            "Entropy": 1.9429743534707526,
            "APLT": 0.45
        },
        {
            "@k": 5,
            "APR": 1.5166666666666666,
            "APR_norm": 0.05055555555555557,
            "Avg_rank": 63.983333333333334,
            "Avg_num_recs": 2.0,
            "Coverage": 0.05755395683453238,
            "Gini": 0.5979166666666667,
            "Entropy": 1.9429743534707526,
            "APLT": 0.45
        },
        {
            "@k": 10,
            "APR": 1.5166666666666666,
            "APR_norm": 0.05055555555555557,
            "Avg_rank": 63.983333333333334,
            "Avg_num_recs": 2.0,
            "Coverage": 0.05755395683453238,
            "Gini": 0.5979166666666667,
            "Entropy": 1.9429743534707526,
            "APLT": 0.45
        }
    ],
    "2003-02-06": [
        {
            "@k": 1,
            "APR": 1.1333333333333333,
            "APR_norm": 0.037777777777777785,
            "Avg_rank": 129.33333333333334,
            "Avg_num_recs": 1.0,
            "Coverage": 0.06093189964157706,
            "Gini": 0.3098039215686275,
            "Entropy": 2.6534180044243567,
            "APLT": 0.8
        },
        {
            "@k": 2,
            "APR": 1.5666666666666667,
            "APR_norm": 0.05222222222222224,
            "Avg_rank": 74.66666666666667,
            "Avg_num_recs": 2.0,
            "Coverage": 0.06093189964157706,
            "Gini": 0.6137254901960785,
            "Entropy": 1.8951672981286787,
            "APLT": 0.4
        },
        {
            "@k": 5,
            "APR": 1.5666666666666667,
            "APR_norm": 0.05222222222222224,
            "Avg_rank": 74.66666666666667,
            "Avg_num_recs": 2.0,
            "Coverage": 0.06093189964157706,
            "Gini": 0.6137254901960785,
            "Entropy": 1.8951672981286787,
            "APLT": 0.4
        },
        {
            "@k": 10,
            "APR": 1.5666666666666667,
            "APR_norm": 0.05222222222222224,
            "Avg_rank": 74.66666666666667,
            "Avg_num_recs": 2.0,
            "Coverage": 0.06093189964157706,
            "Gini": 0.6137254901960785,
            "Entropy": 1.8951672981286787,
            "APLT": 0.4
        }
    ],
    "2003-02-07": [
        {
            "@k": 1,
            "APR": 1.3225806451612903,
            "APR_norm": 0.04266389177939645,
            "Avg_rank": 120.6774193548387,
            "Avg_num_recs": 1.0,
            "Coverage": 0.05982905982905983,
            "Gini": 0.2672811059907834,
            "Entropy": 2.872327462020019,
            "APLT": 0.6774193548387096
        },
        {
            "@k": 2,
            "APR": 1.1612903225806452,
            "APR_norm": 0.037460978147762745,
            "Avg_rank": 233.33870967741936,
            "Avg_num_recs": 2.0,
            "Coverage": 0.06267806267806268,
            "Gini": 0.5821114369501467,
            "Entropy": 2.129310911569955,
            "APLT": 0.8387096774193549
        },
        {
            "@k": 5,
            "APR": 1.1612903225806452,
            "APR_norm": 0.037460978147762745,
            "Avg_rank": 233.33870967741936,
            "Avg_num_recs": 2.0,
            "Coverage": 0.06267806267806268,
            "Gini": 0.5821114369501467,
            "Entropy": 2.129310911569955,
            "APLT": 0.8387096774193549
        },
        {
            "@k": 10,
            "APR": 1.1612903225806452,
            "APR_norm": 0.037460978147762745,
            "Avg_rank": 233.33870967741936,
            "Avg_num_recs": 2.0,
            "Coverage": 0.06267806267806268,
            "Gini": 0.5821114369501467,
            "Entropy": 2.129310911569955,
            "APLT": 0.8387096774193549
        }
    ],
    "2003-02-08": [
        {
            "@k": 1,
            "APR": 1.2083333333333333,
            "APR_norm": 0.05034722222222222,
            "Avg_rank": 145.95833333333334,
            "Avg_num_recs": 1.0,
            "Coverage": 0.050445103857566766,
            "Gini": 0.1715686274509804,
            "Entropy": 2.7737179750213112,
            "APLT": 0.75
        },
        {
            "@k": 2,
            "APR": 1.1041666666666667,
            "APR_norm": 0.04600694444444444,
            "Avg_rank": 232.47916666666666,
            "Avg_num_recs": 2.0,
            "Coverage": 0.050445103857566766,
            "Gini": 0.5392156862745099,
            "Entropy": 1.9925352577923854,
            "APLT": 0.375
        },
        {
            "@k": 5,
            "APR": 1.1041666666666667,
            "APR_norm": 0.04600694444444444,
            "Avg_rank": 232.47916666666666,
            "Avg_num_recs": 2.0,
            "Coverage": 0.050445103857566766,
            "Gini": 0.5392156862745099,
            "Entropy": 1.9925352577923854,
            "APLT": 0.375
        },
        {
            "@k": 10,
            "APR": 1.1041666666666667,
            "APR_norm": 0.04600694444444444,
            "Avg_rank": 232.47916666666666,
            "Avg_num_recs": 2.0,
            "Coverage": 0.050445103857566766,
            "Gini": 0.5392156862745099,
            "Entropy": 1.9925352577923854,
            "APLT": 0.375
        }
    ],
    "2003-02-09": [
        {
            "@k": 1,
            "APR": 1.1304347826086956,
            "APR_norm": 0.0491493383742911,
            "Avg_rank": 150.7826086956522,
            "Avg_num_recs": 1.0,
            "Coverage": 0.043859649122807015,
            "Gini": 0.23188405797101447,
            "Entropy": 2.607805034342705,
            "APLT": 0.8695652173913043
        },
        {
            "@k": 2,
            "APR": 1.065217391304348,
            "APR_norm": 0.04631379962192816,
            "Avg_rank": 235.8913043478261,
            "Avg_num_recs": 2.0,
            "Coverage": 0.04678362573099415,
            "Gini": 0.5461956521739131,
            "Entropy": 1.9970496977312981,
            "APLT": 0.43478260869565216
        },
        {
            "@k": 5,
            "APR": 1.065217391304348,
            "APR_norm": 0.04631379962192816,
            "Avg_rank": 235.8913043478261,
            "Avg_num_recs": 2.0,
            "Coverage": 0.04678362573099415,
            "Gini": 0.5461956521739131,
            "Entropy": 1.9970496977312981,
            "APLT": 0.43478260869565216
        },
        {
            "@k": 10,
            "APR": 1.065217391304348,
            "APR_norm": 0.04631379962192816,
            "Avg_rank": 235.8913043478261,
            "Avg_num_recs": 2.0,
            "Coverage": 0.04678362573099415,
            "Gini": 0.5461956521739131,
            "Entropy": 1.9970496977312981,
            "APLT": 0.43478260869565216
        }
    ],
    "2003-02-10": [
        {
            "@k": 1,
            "APR": 1.2608695652173914,
            "APR_norm": 0.054820415879017,
            "Avg_rank": 136.95652173913044,
            "Avg_num_recs": 1.0,
            "Coverage": 0.05232558139534884,
            "Gini": 0.15700483091787437,
            "Entropy": 2.8341258765552606,
            "APLT": 0.6086956521739131
        },
        {
            "@k": 2,
            "APR": 1.1304347826086956,
            "APR_norm": 0.0491493383742911,
            "Avg_rank": 222.47826086956522,
            "Avg_num_recs": 2.0,
            "Coverage": 0.05232558139534884,
            "Gini": 0.538647342995169,
            "Entropy": 2.019842184881483,
            "APLT": 0.30434782608695654
        },
        {
            "@k": 5,
            "APR": 1.1304347826086956,
            "APR_norm": 0.0491493383742911,
            "Avg_rank": 222.47826086956522,
            "Avg_num_recs": 2.0,
            "Coverage": 0.05232558139534884,
            "Gini": 0.538647342995169,
            "Entropy": 2.019842184881483,
            "APLT": 0.30434782608695654
        },
        {
            "@k": 10,
            "APR": 1.1304347826086956,
            "APR_norm": 0.0491493383742911,
            "Avg_rank": 222.47826086956522,
            "Avg_num_recs": 2.0,
            "Coverage": 0.05232558139534884,
            "Gini": 0.538647342995169,
            "Entropy": 2.019842184881483,
            "APLT": 0.30434782608695654
        }
    ],
    "2003-02-11": [
        {
            "@k": 1,
            "APR": 1.28,
            "APR_norm": 0.05120000000000001,
            "Avg_rank": 175.48,
            "Avg_num_recs": 1.0,
            "Coverage": 0.057356608478802994,
            "Gini": 0.07304347826086957,
            "Entropy": 3.107972275978608,
            "APLT": 0.6
        },
        {
            "@k": 2,
            "APR": 1.14,
            "APR_norm": 0.0456,
            "Avg_rank": 266.74,
            "Avg_num_recs": 2.0,
            "Coverage": 0.057356608478802994,
            "Gini": 0.511304347826087,
            "Entropy": 2.1623610312121797,
            "APLT": 0.3
        },
        {
            "@k": 5,
            "APR": 1.14,
            "APR_norm": 0.0456,
            "Avg_rank": 266.74,
            "Avg_num_recs": 2.0,
            "Coverage": 0.057356608478802994,
            "Gini": 0.511304347826087,
            "Entropy": 2.1623610312121797,
            "APLT": 0.3
        },
        {
            "@k": 10,
            "APR": 1.14,
            "APR_norm": 0.0456,
            "Avg_rank": 266.74,
            "Avg_num_recs": 2.0,
            "Coverage": 0.057356608478802994,
            "Gini": 0.511304347826087,
            "Entropy": 2.1623610312121797,
            "APLT": 0.3
        }
    ],
    "2003-02-12": [
        {
            "@k": 1,
            "APR": 1.0769230769230769,
            "APR_norm": 0.04142011834319527,
            "Avg_rank": 89.15384615384616,
            "Avg_num_recs": 1.0,
            "Coverage": 0.05343511450381679,
            "Gini": 0.29120879120879123,
            "Entropy": 2.4844496430362217,
            "APLT": 0.8076923076923077
        },
        {
            "@k": 2,
            "APR": 1.5384615384615385,
            "APR_norm": 0.0591715976331361,
            "Avg_rank": 51.57692307692308,
            "Avg_num_recs": 2.0,
            "Coverage": 0.05725190839694656,
            "Gini": 0.5692307692307692,
            "Entropy": 1.9353720020780558,
            "APLT": 0.40384615384615385
        },
        {
            "@k": 5,
            "APR": 1.5384615384615385,
            "APR_norm": 0.0591715976331361,
            "Avg_rank": 51.57692307692308,
            "Avg_num_recs": 2.0,
            "Coverage": 0.05725190839694656,
            "Gini": 0.5692307692307692,
            "Entropy": 1.9353720020780558,
            "APLT": 0.40384615384615385
        },
        {
            "@k": 10,
            "APR": 1.5384615384615385,
            "APR_norm": 0.0591715976331361,
            "Avg_rank": 51.57692307692308,
            "Avg_num_recs": 2.0,
            "Coverage": 0.05725190839694656,
            "Gini": 0.5692307692307692,
            "Entropy": 1.9353720020780558,
            "APLT": 0.40384615384615385
        }
    ],
    "2003-02-13": [
        {
            "@k": 1,
            "APR": 1.0740740740740742,
            "APR_norm": 0.03978052126200274,
            "Avg_rank": 73.62962962962963,
            "Avg_num_recs": 1.0,
            "Coverage": 0.06735751295336788,
            "Gini": 0.3190883190883191,
            "Entropy": 2.3942470948184624,
            "APLT": 0.8888888888888888
        },
        {
            "@k": 2,
            "APR": 1.037037037037037,
            "APR_norm": 0.03840877914951988,
            "Avg_rank": 126.31481481481481,
            "Avg_num_recs": 2.0,
            "Coverage": 0.07253886010362694,
            "Gini": 0.5767195767195767,
            "Entropy": 1.8902707279691764,
            "APLT": 0.4444444444444444
        },
        {
            "@k": 5,
            "APR": 1.037037037037037,
            "APR_norm": 0.03840877914951988,
            "Avg_rank": 126.31481481481481,
            "Avg_num_recs": 2.0,
            "Coverage": 0.07253886010362694,
            "Gini": 0.5767195767195767,
            "Entropy": 1.8902707279691764,
            "APLT": 0.4444444444444444
        },
        {
            "@k": 10,
            "APR": 1.037037037037037,
            "APR_norm": 0.03840877914951988,
            "Avg_rank": 126.31481481481481,
            "Avg_num_recs": 2.0,
            "Coverage": 0.07253886010362694,
            "Gini": 0.5767195767195767,
            "Entropy": 1.8902707279691764,
            "APLT": 0.4444444444444444
        }
    ],
    "2003-02-14": [
        {
            "@k": 1,
            "APR": 1.0769230769230769,
            "APR_norm": 0.04142011834319527,
            "Avg_rank": 104.8076923076923,
            "Avg_num_recs": 1.0,
            "Coverage": 0.07860262008733625,
            "Gini": 0.2008547008547009,
            "Entropy": 2.8114194983013414,
            "APLT": 0.8846153846153846
        },
        {
            "@k": 2,
            "APR": 1.0384615384615385,
            "APR_norm": 0.03994082840236687,
            "Avg_rank": 157.40384615384616,
            "Avg_num_recs": 2.0,
            "Coverage": 0.08296943231441048,
            "Gini": 0.5425101214574899,
            "Entropy": 2.0988569297106157,
            "APLT": 0.4423076923076923
        },
        {
            "@k": 5,
            "APR": 1.0384615384615385,
            "APR_norm": 0.03994082840236687,
            "Avg_rank": 157.40384615384616,
            "Avg_num_recs": 2.0,
            "Coverage": 0.08296943231441048,
            "Gini": 0.5425101214574899,
            "Entropy": 2.0988569297106157,
            "APLT": 0.4423076923076923
        },
        {
            "@k": 10,
            "APR": 1.0384615384615385,
            "APR_norm": 0.03994082840236687,
            "Avg_rank": 157.40384615384616,
            "Avg_num_recs": 2.0,
            "Coverage": 0.08296943231441048,
            "Gini": 0.5425101214574899,
            "Entropy": 2.0988569297106157,
            "APLT": 0.4423076923076923
        }
    ],
    "2003-02-15": [
        {
            "@k": 1,
            "APR": 1.0833333333333333,
            "APR_norm": 0.04513888888888889,
            "Avg_rank": 94.25,
            "Avg_num_recs": 1.0,
            "Coverage": 0.08888888888888889,
            "Gini": 0.14583333333333331,
            "Entropy": 2.9252027641711082,
            "APLT": 0.7916666666666666
        },
        {
            "@k": 2,
            "APR": 1.0416666666666667,
            "APR_norm": 0.04340277777777777,
            "Avg_rank": 151.625,
            "Avg_num_recs": 2.0,
            "Coverage": 0.09333333333333334,
            "Gini": 0.5218253968253969,
            "Entropy": 2.1557485626454995,
            "APLT": 0.3958333333333333
        },
        {
            "@k": 5,
            "APR": 1.0416666666666667,
            "APR_norm": 0.04340277777777777,
            "Avg_rank": 151.625,
            "Avg_num_recs": 2.0,
            "Coverage": 0.09333333333333334,
            "Gini": 0.5218253968253969,
            "Entropy": 2.1557485626454995,
            "APLT": 0.3958333333333333
        },
        {
            "@k": 10,
            "APR": 1.0416666666666667,
            "APR_norm": 0.04340277777777777,
            "Avg_rank": 151.625,
            "Avg_num_recs": 2.0,
            "Coverage": 0.09333333333333334,
            "Gini": 0.5218253968253969,
            "Entropy": 2.1557485626454995,
            "APLT": 0.3958333333333333
        }
    ],
    "2003-02-16": [
        {
            "@k": 1,
            "APR": 1.0,
            "APR_norm": 0.05000000000000001,
            "Avg_rank": 71.45,
            "Avg_num_recs": 1.0,
            "Coverage": 0.08441558441558442,
            "Gini": 0.2692307692307692,
            "Entropy": 2.4150521219178076,
            "APLT": 0.7
        },
        {
            "@k": 2,
            "APR": 1.0,
            "APR_norm": 0.05000000000000001,
            "Avg_rank": 105.225,
            "Avg_num_recs": 2.0,
            "Coverage": 0.09090909090909091,
            "Gini": 0.5535714285714286,
            "Entropy": 1.9006732415188488,
            "APLT": 0.35
        },
        {
            "@k": 5,
            "APR": 1.0,
            "APR_norm": 0.05000000000000001,
            "Avg_rank": 105.225,
            "Avg_num_recs": 2.0,
            "Coverage": 0.09090909090909091,
            "Gini": 0.5535714285714286,
            "Entropy": 1.9006732415188488,
            "APLT": 0.35
        },
        {
            "@k": 10,
            "APR": 1.0,
            "APR_norm": 0.05000000000000001,
            "Avg_rank": 105.225,
            "Avg_num_recs": 2.0,
            "Coverage": 0.09090909090909091,
            "Gini": 0.5535714285714286,
            "Entropy": 1.9006732415188488,
            "APLT": 0.35
        }
    ],
    "2003-02-17": [
        {
            "@k": 1,
            "APR": 1.0,
            "APR_norm": 0.058823529411764705,
            "Avg_rank": 36.529411764705884,
            "Avg_num_recs": 1.0,
            "Coverage": 0.10112359550561797,
            "Gini": 0.3137254901960784,
            "Entropy": 2.0177460728092216,
            "APLT": 0.9411764705882353
        },
        {
            "@k": 2,
            "APR": 1.0,
            "APR_norm": 0.058823529411764705,
            "Avg_rank": 60.76470588235294,
            "Avg_num_recs": 2.0,
            "Coverage": 0.11235955056179775,
            "Gini": 0.5411764705882354,
            "Entropy": 1.7020202169645562,
            "APLT": 0.47058823529411764
        },
        {
            "@k": 5,
            "APR": 1.0,
            "APR_norm": 0.058823529411764705,
            "Avg_rank": 60.76470588235294,
            "Avg_num_recs": 2.0,
            "Coverage": 0.11235955056179775,
            "Gini": 0.5411764705882354,
            "Entropy": 1.7020202169645562,
            "APLT": 0.47058823529411764
        },
        {
            "@k": 10,
            "APR": 1.0,
            "APR_norm": 0.058823529411764705,
            "Avg_rank": 60.76470588235294,
            "Avg_num_recs": 2.0,
            "Coverage": 0.11235955056179775,
            "Gini": 0.5411764705882354,
            "Entropy": 1.7020202169645562,
            "APLT": 0.47058823529411764
        }
    ],
    "2003-02-18": [
        {
            "@k": 1,
            "APR": 1.0,
            "APR_norm": 0.04545454545454544,
            "Avg_rank": 47.0,
            "Avg_num_recs": 1.0,
            "Coverage": 0.07633587786259542,
            "Gini": 0.1818181818181818,
            "Entropy": 2.239745866608458,
            "APLT": 0.8636363636363636
        },
        {
            "@k": 2,
            "APR": 1.0,
            "APR_norm": 0.04545454545454544,
            "Avg_rank": 82.5,
            "Avg_num_recs": 2.0,
            "Coverage": 0.08396946564885496,
            "Gini": 0.49173553719008267,
            "Entropy": 1.813020113864174,
            "APLT": 0.4318181818181818
        },
        {
            "@k": 5,
            "APR": 1.0,
            "APR_norm": 0.04545454545454544,
            "Avg_rank": 82.5,
            "Avg_num_recs": 2.0,
            "Coverage": 0.08396946564885496,
            "Gini": 0.49173553719008267,
            "Entropy": 1.813020113864174,
            "APLT": 0.4318181818181818
        },
        {
            "@k": 10,
            "APR": 1.0,
            "APR_norm": 0.04545454545454544,
            "Avg_rank": 82.5,
            "Avg_num_recs": 2.0,
            "Coverage": 0.08396946564885496,
            "Gini": 0.49173553719008267,
            "Entropy": 1.813020113864174,
            "APLT": 0.4318181818181818
        }
    ],
    "2003-02-19": [
        {
            "@k": 1,
            "APR": 1.125,
            "APR_norm": 0.03515625,
            "Avg_rank": 43.90625,
            "Avg_num_recs": 1.0,
            "Coverage": 0.15306122448979592,
            "Gini": 0.22083333333333333,
            "Entropy": 2.6148064920062897,
            "APLT": 0.6875
        },
        {
            "@k": 2,
            "APR": 1.0625,
            "APR_norm": 0.033203125,
            "Avg_rank": 66.953125,
            "Avg_num_recs": 2.0,
            "Coverage": 0.16326530612244897,
            "Gini": 0.541015625,
            "Entropy": 2.0005504265630902,
            "APLT": 0.34375
        },
        {
            "@k": 5,
            "APR": 1.0625,
            "APR_norm": 0.033203125,
            "Avg_rank": 66.953125,
            "Avg_num_recs": 2.0,
            "Coverage": 0.16326530612244897,
            "Gini": 0.541015625,
            "Entropy": 2.0005504265630902,
            "APLT": 0.34375
        },
        {
            "@k": 10,
            "APR": 1.0625,
            "APR_norm": 0.033203125,
            "Avg_rank": 66.953125,
            "Avg_num_recs": 2.0,
            "Coverage": 0.16326530612244897,
            "Gini": 0.541015625,
            "Entropy": 2.0005504265630902,
            "APLT": 0.34375
        }
    ],
    "2003-02-20": [
        {
            "@k": 1,
            "APR": 1.1818181818181819,
            "APR_norm": 0.035812672176308534,
            "Avg_rank": 42.75757575757576,
            "Avg_num_recs": 1.0,
            "Coverage": 0.14049586776859505,
            "Gini": 0.29590017825311943,
            "Entropy": 2.6824820764651935,
            "APLT": 0.6666666666666666
        },
        {
            "@k": 2,
            "APR": 1.0909090909090908,
            "APR_norm": 0.03305785123966942,
            "Avg_rank": 78.37878787878788,
            "Avg_num_recs": 2.0,
            "Coverage": 0.1487603305785124,
            "Gini": 0.5841750841750842,
            "Entropy": 2.034388218792542,
            "APLT": 0.3333333333333333
        },
        {
            "@k": 5,
            "APR": 1.0909090909090908,
            "APR_norm": 0.03305785123966942,
            "Avg_rank": 78.37878787878788,
            "Avg_num_recs": 2.0,
            "Coverage": 0.1487603305785124,
            "Gini": 0.5841750841750842,
            "Entropy": 2.034388218792542,
            "APLT": 0.3333333333333333
        },
        {
            "@k": 10,
            "APR": 1.0909090909090908,
            "APR_norm": 0.03305785123966942,
            "Avg_rank": 78.37878787878788,
            "Avg_num_recs": 2.0,
            "Coverage": 0.1487603305785124,
            "Gini": 0.5841750841750842,
            "Entropy": 2.034388218792542,
            "APLT": 0.3333333333333333
        }
    ],
    "2003-02-21": [
        {
            "@k": 1,
            "APR": 1.2,
            "APR_norm": 0.03428571428571428,
            "Avg_rank": 57.42857142857143,
            "Avg_num_recs": 1.0,
            "Coverage": 0.12048192771084337,
            "Gini": 0.2757142857142857,
            "Entropy": 2.8618137085472295,
            "APLT": 0.8285714285714286
        },
        {
            "@k": 2,
            "APR": 1.1,
            "APR_norm": 0.03142857142857142,
            "Avg_rank": 109.71428571428571,
            "Avg_num_recs": 2.0,
            "Coverage": 0.12650602409638553,
            "Gini": 0.5836734693877551,
            "Entropy": 2.12405403483356,
            "APLT": 0.4142857142857143
        },
        {
            "@k": 5,
            "APR": 1.1,
            "APR_norm": 0.03142857142857142,
            "Avg_rank": 109.71428571428571,
            "Avg_num_recs": 2.0,
            "Coverage": 0.12650602409638553,
            "Gini": 0.5836734693877551,
            "Entropy": 2.12405403483356,
            "APLT": 0.4142857142857143
        },
        {
            "@k": 10,
            "APR": 1.1,
            "APR_norm": 0.03142857142857142,
            "Avg_rank": 109.71428571428571,
            "Avg_num_recs": 2.0,
            "Coverage": 0.12650602409638553,
            "Gini": 0.5836734693877551,
            "Entropy": 2.12405403483356,
            "APLT": 0.4142857142857143
        }
    ],
    "2003-02-22": [
        {
            "@k": 1,
            "APR": 1.368421052631579,
            "APR_norm": 0.03601108033240998,
            "Avg_rank": 84.07894736842105,
            "Avg_num_recs": 1.0,
            "Coverage": 0.13366336633663367,
            "Gini": 0.2222222222222222,
            "Entropy": 3.186039305063143,
            "APLT": 0.5526315789473685
        },
        {
            "@k": 2,
            "APR": 1.1842105263157894,
            "APR_norm": 0.0311634349030471,
            "Avg_rank": 79.53947368421052,
            "Avg_num_recs": 2.0,
            "Coverage": 0.13861386138613863,
            "Gini": 0.5714285714285714,
            "Entropy": 2.286166833091516,
            "APLT": 0.7763157894736842
        },
        {
            "@k": 5,
            "APR": 1.1842105263157894,
            "APR_norm": 0.0311634349030471,
            "Avg_rank": 79.53947368421052,
            "Avg_num_recs": 2.0,
            "Coverage": 0.13861386138613863,
            "Gini": 0.5714285714285714,
            "Entropy": 2.286166833091516,
            "APLT": 0.7763157894736842
        },
        {
            "@k": 10,
            "APR": 1.1842105263157894,
            "APR_norm": 0.0311634349030471,
            "Avg_rank": 79.53947368421052,
            "Avg_num_recs": 2.0,
            "Coverage": 0.13861386138613863,
            "Gini": 0.5714285714285714,
            "Entropy": 2.286166833091516,
            "APLT": 0.7763157894736842
        }
    ],
    "2003-02-23": [
        {
            "@k": 1,
            "APR": 1.25,
            "APR_norm": 0.03125,
            "Avg_rank": 77.475,
            "Avg_num_recs": 1.0,
            "Coverage": 0.11794871794871795,
            "Gini": 0.27391304347826084,
            "Entropy": 2.9979104369133687,
            "APLT": 0.7
        },
        {
            "@k": 2,
            "APR": 1.125,
            "APR_norm": 0.028125,
            "Avg_rank": 115.7375,
            "Avg_num_recs": 2.0,
            "Coverage": 0.11794871794871795,
            "Gini": 0.6130434782608696,
            "Entropy": 2.056095024713362,
            "APLT": 0.85
        },
        {
            "@k": 5,
            "APR": 1.125,
            "APR_norm": 0.028125,
            "Avg_rank": 115.7375,
            "Avg_num_recs": 2.0,
            "Coverage": 0.11794871794871795,
            "Gini": 0.6130434782608696,
            "Entropy": 2.056095024713362,
            "APLT": 0.85
        },
        {
            "@k": 10,
            "APR": 1.125,
            "APR_norm": 0.028125,
            "Avg_rank": 115.7375,
            "Avg_num_recs": 2.0,
            "Coverage": 0.11794871794871795,
            "Gini": 0.6130434782608696,
            "Entropy": 2.056095024713362,
            "APLT": 0.85
        }
    ],
    "2003-02-24": [
        {
            "@k": 1,
            "APR": 1.2222222222222223,
            "APR_norm": 0.03395061728395061,
            "Avg_rank": 88.44444444444444,
            "Avg_num_recs": 1.0,
            "Coverage": 0.09574468085106383,
            "Gini": 0.3209876543209876,
            "Entropy": 2.714785726577837,
            "APLT": 0.5555555555555556
        },
        {
            "@k": 2,
            "APR": 1.1111111111111112,
            "APR_norm": 0.030864197530864185,
            "Avg_rank": 118.72222222222223,
            "Avg_num_recs": 2.0,
            "Coverage": 0.09574468085106383,
            "Gini": 0.6049382716049383,
            "Entropy": 1.9866889190791923,
            "APLT": 0.7777777777777778
        },
        {
            "@k": 5,
            "APR": 1.1111111111111112,
            "APR_norm": 0.030864197530864185,
            "Avg_rank": 118.72222222222223,
            "Avg_num_recs": 2.0,
            "Coverage": 0.09574468085106383,
            "Gini": 0.6049382716049383,
            "Entropy": 1.9866889190791923,
            "APLT": 0.7777777777777778
        },
        {
            "@k": 10,
            "APR": 1.1111111111111112,
            "APR_norm": 0.030864197530864185,
            "Avg_rank": 118.72222222222223,
            "Avg_num_recs": 2.0,
            "Coverage": 0.09574468085106383,
            "Gini": 0.6049382716049383,
            "Entropy": 1.9866889190791923,
            "APLT": 0.7777777777777778
        }
    ],
    "2003-02-25": [
        {
            "@k": 1,
            "APR": 1.3225806451612903,
            "APR_norm": 0.04266389177939645,
            "Avg_rank": 69.25806451612904,
            "Avg_num_recs": 1.0,
            "Coverage": 0.09424083769633508,
            "Gini": 0.29569892473118276,
            "Entropy": 2.7294416656358735,
            "APLT": 0.7096774193548387
        },
        {
            "@k": 2,
            "APR": 1.1612903225806452,
            "APR_norm": 0.037460978147762745,
            "Avg_rank": 113.62903225806451,
            "Avg_num_recs": 2.0,
            "Coverage": 0.09947643979057591,
            "Gini": 0.5874363327674024,
            "Entropy": 2.0578680133778824,
            "APLT": 0.3548387096774194
        },
        {
            "@k": 5,
            "APR": 1.1612903225806452,
            "APR_norm": 0.037460978147762745,
            "Avg_rank": 113.62903225806451,
            "Avg_num_recs": 2.0,
            "Coverage": 0.09947643979057591,
            "Gini": 0.5874363327674024,
            "Entropy": 2.0578680133778824,
            "APLT": 0.3548387096774194
        },
        {
            "@k": 10,
            "APR": 1.1612903225806452,
            "APR_norm": 0.037460978147762745,
            "Avg_rank": 113.62903225806451,
            "Avg_num_recs": 2.0,
            "Coverage": 0.09947643979057591,
            "Gini": 0.5874363327674024,
            "Entropy": 2.0578680133778824,
            "APLT": 0.3548387096774194
        }
    ],
    "2003-02-26": [
        {
            "@k": 1,
            "APR": 1.3448275862068966,
            "APR_norm": 0.04637336504161713,
            "Avg_rank": 108.89655172413794,
            "Avg_num_recs": 1.0,
            "Coverage": 0.058823529411764705,
            "Gini": 0.29764065335753176,
            "Entropy": 2.709767451293795,
            "APLT": 0.6551724137931034
        },
        {
            "@k": 2,
            "APR": 1.1724137931034482,
            "APR_norm": 0.04042806183115339,
            "Avg_rank": 193.44827586206895,
            "Avg_num_recs": 2.0,
            "Coverage": 0.058823529411764705,
            "Gini": 0.604355716878403,
            "Entropy": 1.9724387962024135,
            "APLT": 0.3275862068965517
        },
        {
            "@k": 5,
            "APR": 1.1724137931034482,
            "APR_norm": 0.04042806183115339,
            "Avg_rank": 193.44827586206895,
            "Avg_num_recs": 2.0,
            "Coverage": 0.058823529411764705,
            "Gini": 0.604355716878403,
            "Entropy": 1.9724387962024135,
            "APLT": 0.3275862068965517
        },
        {
            "@k": 10,
            "APR": 1.1724137931034482,
            "APR_norm": 0.04042806183115339,
            "Avg_rank": 193.44827586206895,
            "Avg_num_recs": 2.0,
            "Coverage": 0.058823529411764705,
            "Gini": 0.604355716878403,
            "Entropy": 1.9724387962024135,
            "APLT": 0.3275862068965517
        }
    ],
    "2003-02-27": [
        {
            "@k": 1,
            "APR": 1.0434782608695652,
            "APR_norm": 0.04536862003780717,
            "Avg_rank": 132.65217391304347,
            "Avg_num_recs": 1.0,
            "Coverage": 0.053763440860215055,
            "Gini": 0.2608695652173913,
            "Entropy": 2.5702812857620385,
            "APLT": 0.6956521739130435
        },
        {
            "@k": 2,
            "APR": 1.0217391304347827,
            "APR_norm": 0.044423440453686194,
            "Avg_rank": 88.82608695652173,
            "Avg_num_recs": 2.0,
            "Coverage": 0.053763440860215055,
            "Gini": 0.5739130434782608,
            "Entropy": 1.887919889484872,
            "APLT": 0.8478260869565217
        },
        {
            "@k": 5,
            "APR": 1.0217391304347827,
            "APR_norm": 0.044423440453686194,
            "Avg_rank": 88.82608695652173,
            "Avg_num_recs": 2.0,
            "Coverage": 0.053763440860215055,
            "Gini": 0.5739130434782608,
            "Entropy": 1.887919889484872,
            "APLT": 0.8478260869565217
        },
        {
            "@k": 10,
            "APR": 1.0217391304347827,
            "APR_norm": 0.044423440453686194,
            "Avg_rank": 88.82608695652173,
            "Avg_num_recs": 2.0,
            "Coverage": 0.053763440860215055,
            "Gini": 0.5739130434782608,
            "Entropy": 1.887919889484872,
            "APLT": 0.8478260869565217
        }
    ],
    "2003-02-28": [
        {
            "@k": 1,
            "APR": 1.1666666666666667,
            "APR_norm": 0.048611111111111105,
            "Avg_rank": 133.91666666666666,
            "Avg_num_recs": 1.0,
            "Coverage": 0.05673758865248227,
            "Gini": 0.23437500000000003,
            "Entropy": 2.6581934449279867,
            "APLT": 0.625
        },
        {
            "@k": 2,
            "APR": 1.0833333333333333,
            "APR_norm": 0.04513888888888889,
            "Avg_rank": 135.95833333333334,
            "Avg_num_recs": 2.0,
            "Coverage": 0.05673758865248227,
            "Gini": 0.5651041666666669,
            "Entropy": 1.9347729927457236,
            "APLT": 0.8125
        },
        {
            "@k": 5,
            "APR": 1.0833333333333333,
            "APR_norm": 0.04513888888888889,
            "Avg_rank": 135.95833333333334,
            "Avg_num_recs": 2.0,
            "Coverage": 0.05673758865248227,
            "Gini": 0.5651041666666669,
            "Entropy": 1.9347729927457236,
            "APLT": 0.8125
        },
        {
            "@k": 10,
            "APR": 1.0833333333333333,
            "APR_norm": 0.04513888888888889,
            "Avg_rank": 135.95833333333334,
            "Avg_num_recs": 2.0,
            "Coverage": 0.05673758865248227,
            "Gini": 0.5651041666666669,
            "Entropy": 1.9347729927457236,
            "APLT": 0.8125
        }
    ]
}